skill_ovos_bandcamp/LICENSE
skill_ovos_bandcamp/MANIFEST.in
skill_ovos_bandcamp/README.md
skill_ovos_bandcamp/__init__.py
skill_ovos_bandcamp/version.py
skill_ovos_bandcamp/locale/en-us/bandcamp.voc
skill_ovos_bandcamp/locale/en-us/bandcamp_skill.voc
skill_ovos_bandcamp/locale/en-us/skill.json
skill_ovos_bandcamp/locale/eu/bandcamp.voc
skill_ovos_bandcamp/locale/gl-es/bandcamp.voc
skill_ovos_bandcamp/res/logo.png
skill_ovos_bandcamp/skill_bandcamp.egg-info/PKG-INFO
skill_ovos_bandcamp/skill_bandcamp.egg-info/SOURCES.txt
skill_ovos_bandcamp/skill_bandcamp.egg-info/dependency_links.txt
skill_ovos_bandcamp/skill_bandcamp.egg-info/entry_points.txt
skill_ovos_bandcamp/skill_bandcamp.egg-info/requires.txt
skill_ovos_bandcamp/skill_bandcamp.egg-info/top_level.txt
skill_bandcamp-0.0.8.dist-info/LICENSE
skill_bandcamp-0.0.8.dist-info/METADATA
skill_bandcamp-0.0.8.dist-info/WHEEL
skill_bandcamp-0.0.8.dist-info/entry_points.txt
skill_bandcamp-0.0.8.dist-info/top_level.txt
skill_bandcamp-0.0.8.dist-info/RECORD
