Metadata-Version: 2.1
Name: skill-bandcamp
Version: 0.0.8
Summary: ovos common play bandcamp skill plugin
Home-page: https://github.com/OpenVoiceOS/skill-ovos-bandcamp
Author: JarbasAi
Author-email: jarbasai@mailfence.com
License: Apache-2.0
Keywords: ovos skill plugin
Platform: UNKNOWN
Requires-Dist: py-bandcamp>=0.7.0
Requires-Dist: ovos-utils>=0.1.0
Requires-Dist: ovos-workshop>=0.0.16
